{
  "pageUrl": "https://hamilton-exteriors.com/service-areas/napa-county-ca/american-canyon-ca/custom-homes",
  "pagePurpose": "Convert American Canyon homeowners searching for custom home builder services. Bottom-of-funnel commercial intent.",
  "pageType": "service-area-city-service",
  "citySlug": "american-canyon-ca",
  "service": "custom-homes",
  "primaryKeywords": [
    {
      "kw": "american canyon custom home builder",
      "priority": 1,
      "intent": "commercial"
    },
    {
      "kw": "custom home builder american canyon",
      "priority": 1,
      "intent": "commercial"
    },
    {
      "kw": "custom home construction american canyon",
      "priority": 1,
      "intent": "commercial"
    }
  ],
  "secondaryKeywords": [
    {
      "kw": "custom home builder american canyon ca",
      "priority": 2,
      "intent": "commercial"
    },
    {
      "kw": "custom homes contractor american canyon",
      "priority": 2,
      "intent": "commercial"
    }
  ],
  "currentRankings": {},
  "competitorSet": [],
  "contentBrief": null,
  "metrics": {
    "indexedAt": null,
    "t14": null,
    "t30": null,
    "t60": null
  },
  "status": "pending",
  "iterations": 0,
  "lastError": null,
  "pageSlug": "sa-city-service__american-canyon-ca__custom-homes"
}